CHANGES.txt
MANIFEST.in
README.md
setup.py
GeobricksGeoserverManager.egg-info/PKG-INFO
GeobricksGeoserverManager.egg-info/SOURCES.txt
GeobricksGeoserverManager.egg-info/dependency_links.txt
GeobricksGeoserverManager.egg-info/requires.txt
GeobricksGeoserverManager.egg-info/top_level.txt
geobricks_geoserver_manager/.gitignore
geobricks_geoserver_manager/__init__.py
geobricks_geoserver_manager/config/__init__.py
geobricks_geoserver_manager/config/config.py
geobricks_geoserver_manager/core/.gitignore
geobricks_geoserver_manager/core/__init__.py
geobricks_geoserver_manager/core/geoserver_manager_core.py
geobricks_geoserver_manager/utils/__init__.py
geobricks_geoserver_manager/utils/log.py
test/__init__.py
test/geosever_manager_test.py
test/config/__init__.py
test/config/config.py