Metadata-Version: 1.0
Name: GeobricksGeoserverManager
Version: 0.1.0
Summary: Geobricks library to manage Geoserver clusters.
Home-page: http://pypi.python.org/pypi/GeobricksGeoserverManager/
Author: Simone Murzilli; Guido Barbaglia
Author-email: geobrickspy@gmail.com
License: LICENSE.txt
Keywords: geobricks,geoserver,gis,gsconfig
Platform: UNKNOWN
